pykid/__init__.py
pykid/demo/__init__.py
pykid/demo/hello.py
pykid-0.0.dist-info/METADATA
pykid-0.0.dist-info/WHEEL
pykid-0.0.dist-info/top_level.txt
pykid-0.0.dist-info/RECORD
