Metadata-Version: 2.1
Name: pykid
Version: 0.0
Summary: This is a kid's python library.
Home-page: https://pymilk.com/
Author: pykid
Author-email: vaporzfy@sina.com
License: GPL2
Platform: UNKNOWN
